{"n/SG17Zct8bLNIB1Xkewdg==":"manual%20marca%20terras.pdf%20(1)-146x103.png","mjZkUH8M/teV3dcdf+pDKQ==":"manual%20marca%20terras.pdf%20(1)-146x103.png","nod+rf6h7hXHn5JGGhKHUw==":"design%20sem%20nome%20(6)-2000x1000.png","JcuEnXcLboCmvyKWwp5gpA==":"apresenta%C3%A7%C3%A3o%20cresol%20-%2001.03.2024-1160x653.png","o+b2xL6T//ZgncY8hvTwDQ==":"apresenta%C3%A7%C3%A3o%20cresol%20-%2001.03.2024-1160x653.png","fx3ZuJ8zPgcfBoCdgtLrjg==":"design%20sem%20nome%20(8)-1568x882.png","Fv1INe4zkLwu1fkNwjFWKA==":"design%20sem%20nome%20(9)-1080x1080.png","PW5OsU26Ui/ufdUoHxl/jQ==":"design%20sem%20nome%20(11)-1568x882.png","iHmSpQHRxmY9SMnL3rzVmQ==":"design%20sem%20nome%20(11)-1568x882.png","pKWd6LSBQfWMLHt+irvprA==":"apresenta%C3%A7%C3%A3o%20comercial%20-%20terras%20app%20solutions%20-%20a%C3%A7a%C3%AD-1920x1080.png","6FgtiWqnG/a+cKRIkfpjpw==":"apresenta%C3%A7%C3%A3o%20comercial%20-%20terras%20app%20solutions%20-%20a%C3%A7a%C3%AD-1920x1080.png","NsYFC9r92smD+7S7bS1iNA==":"apresenta%C3%A7%C3%A3o%20comercial%20-%20terras%20app%20solutions%20-%20a%C3%A7a%C3%AD-1920x1080.png","zTC2pKvFkxYn7kcykTdvzA==":"6-1538x865.png","M+EEleeb5a0cbBq6rtLMmw==":"7-1538x865.png","SJ31d0bncgPLZGnXIx13Cw==":"6-596x596.jpeg","lgDBFQqdUhP5KI/ZdRV5JQ==":"4-596x596.jpeg","QR8c0Th1XsPS5Su/RyV2tQ==":"5-596x596.jpeg","rT6xxqYEBILe05q3CHJUTw==":"1-240x240.png","kvehRsI94mfSeaOTFCVm1A==":"2-240x240.png","4PKD2Eb7xaFory42/PbhXA==":"3-240x240.png","Z6xF8yc1ELFh4MZ5iA6qrw==":"design%20sem%20nome%20(13)-240x240.png","zg5y5A/VRMQynBgm6EIe0A==":"5-1-240x240.png","ridh6PYYZ4W6PyHyFlKHHg==":"6-1-240x240.png","xz8RhF3A6liDXpZ1+Uqv6A==":"7-1-240x240.png","FdVT8a1KUljlRvquFvOgXA==":"8-1-240x240.png","p/3awTLj5NVJMm0d1aOIHQ==":"9-1-240x240.png","2wF0k5Z+Q86QjCZkIbeABw==":"10-1-240x240.png","+5YsS/tQGhcIC7vxMdSupQ==":"design%20sem%20nome%20(13)-240x240.png","NCU8N0sTtxIkxQl82i0vag==":"design%20sem%20nome%20(14)-1916x1078.png","hidLejN3sID2+SrposJwVw==":"design%20sem%20nome%20(14)-1916x1078.png","dndAKjTnsioU7Pg0uJ0v/Q==":"design%20sem%20nome%20(14)-1920x1080.png","vo+T4f9k/ZzwNMsNl3PZyA==":"design%20sem%20nome%20(14)-1916x1078.png","QvIdDt7/1iM22qYQR7egiw==":"design%20sem%20nome%20(14)-1916x1078.png","GfZN8RE5yYyEFemTA5NAqw==":"design%20sem%20nome%20(14)-1916x1078.png","/as7jkmEhaI8gcmzoayX1g==":"design%20sem%20nome%20(14)-1916x1078.png","JAsnBM61fSQ6Kj7rLBU9tQ==":"design%20sem%20nome%20(14)-1160x653.png","ZJep1AyTAdQQS48MIpVbrw==":"design%20sem%20nome%20(14)-1920x1080.png","9A67c2/ZKCjX+L9SKWVDlA==":"desenvolvendo%20solu%C3%87%C3%95es%20sustent%C3%81veis%20para%20oc%20(2)-1920x1080.png","MM5vgpllyC4hgUoO2Pz74g==":"desenvolvendo%20solu%C3%87%C3%95es%20sustent%C3%81veis%20para%20oc%20(2)-1920x1080.png","m6Uc7V71EmIazzmvvdxL5w==":"desenvolvendo%20solu%C3%87%C3%95es%20sustent%C3%81veis%20para%20oc%20(3)-1920x1080.png","av2jzSM69ZVLjd3mvsJwvA==":"desenvolvendo%20solu%C3%87%C3%95es%20sustent%C3%81veis%20para%20oc%20(4)-1920x1080.png","GKH2zSOMMfBxN9hdoaSgJQ==":"desenvolvendo%20solu%C3%87%C3%95es%20sustent%C3%81veis%20para%20oc%20(4)-1920x1080.png","dt7eQGfnu4rGND4nHxjoVA==":"desenvolvendo%20solu%C3%87%C3%95es%20sustent%C3%81veis%20para%20oc%20(4)-1920x1080.png","ygPEv9jNhBZ0gO325AYZcQ==":"design%20sem%20nome%20(14)-1160x653.png","ucQXLR938DZ/HnLEgROXHQ==":"6-1-600x600.png","RFC+cXx+Minnq3Dw6o5Y1g==":"7-600x600.png","KjwaSP8AnkocjzQPcX9Uaw==":"8-600x600.png","BnOEZmMtGPcXMI5HVlI0OA==":"10-600x600.png","z8Ym8mp0O33VO/6xuNOeIg==":"9-480x480.png","LAyWkBG/5NvXW/tenXZxgw==":"design%20sem%20nome%20(14)-1916x1078.png","IA8+4k9O4R6eJH2tHou1wA==":"desenvolvendo%20solu%C3%87%C3%95es%20sustent%C3%81veis%20para%20oc%20(9)-1920x1080.png","ye+K1F9py8s7vi3/Q8HgyQ==":"desenvolvendo%20solu%C3%87%C3%95es%20sustent%C3%81veis%20para%20oc%20(9)-1920x1080.png","e+LDGQ/63vrV+/IViyGvWQ==":"desenvolvendo%20solu%C3%87%C3%95es%20sustent%C3%81veis%20para%20oc%20(9)-1920x1080.png","VpPryNx74EYmxqUAito+hw==":"desenvolvendo%20solu%C3%87%C3%95es%20sustent%C3%81veis%20para%20oc%20(9)-1920x1080.png","oDoC9Ncc1h9be2i+KTJriw==":"desenvolvendo%20solu%C3%87%C3%95es%20sustent%C3%81veis%20para%20oc%20(10)-1920x1080.png","/BOPgn5mT6TJaT1uCAwhMw==":"desenvolvendo%20solu%C3%87%C3%95es%20sustent%C3%81veis%20para%20oc%20(10)-1920x1080.png","j3nLIYBwcFUKmLheTa0Z0Q==":"desenvolvendo%20solu%C3%87%C3%95es%20sustent%C3%81veis%20para%20oc%20(10)-1920x1080.png","vvJafFOcpcin6tYJ+xn8PQ==":"captura%20de%20tela%202024-04-19%20a%CC%80s%2015.21.06-2000x544.png","0v/tZ+50qqGSV8b3N/lewg==":"desenvolvendo%20solu%C3%87%C3%95es%20sustent%C3%81veis%20para%20oc%20(12)-1920x1080.png","dDad4D5ByU0yxE0GHwsQBw==":"pexels-tom-fisk-1483880-2000x1123.jpg","08w5L0svCMlstt/mitSMdQ==":"design%20sem%20nome%20(15)-596x596.png","RVcDYHMOuKI+/klP1KL8xA==":"design%20sem%20nome%20(15)-112x112.png","2hUpA9KC248+G7DAEWAsyA==":"design%20sem%20nome%20(17)-80x80.png","DrI4j6TBZ8IvFzCvXslJoQ==":"design%20sem%20nome%20(17)-80x80.png","s+OXjGOSWx5JvgjJyfQ0UQ==":"design%20sem%20nome%20(16)-255x255.png","EbkbmNOHzeI8kSjoRy0QHA==":"mbr-476x697.jpg","5z5tz3zNBAXQj7mm1m67Kw==":"desenvolvendo%20solu%C3%87%C3%95es%20sustent%C3%81veis%20para%20oc%20(9)-1916x1078.png","gmaakFB7x7JiMCAKgcOPPQ==":"5-816x816.jpeg","3GLtrjsrUgY+aLpgme4ZOg==":"4-816x816.jpeg","pKUMedGnXd2nDWmRkCeKPg==":"6-816x816.jpeg"}